pyadbcxy/__init__.py
pyadbcxy/elementary_functions.py
pyadbcxy/forward.py
pyadbcxy/reverse.py
pyadbcxy/variable.py
pyadbcxy-0.0.6.dist-info/LICENSE
pyadbcxy-0.0.6.dist-info/METADATA
pyadbcxy-0.0.6.dist-info/WHEEL
pyadbcxy-0.0.6.dist-info/top_level.txt
pyadbcxy-0.0.6.dist-info/RECORD
