Metadata-Version: 2.1
Name: pyadbcxy
Version: 0.0.6
Summary: An automatic differentiation package
Home-page: https://github.com/cs107-BCXY/cs107-FinalProject
Author: Xiang Bai, Charlie Harrington, Yaxin Lei, Bowen Zhu
License: MIT
Project-URL: Bug Tracker, https://github.com/cs107-BCXY/cs107-FinalProject/issues
Platform: UNKNOWN
Classifier: Programming Language :: Python :: 3
Classifier: License :: OSI Approved :: MIT License
Classifier: Operating System :: OS Independent
Requires-Python: >=3.8
License-File: LICENSE
Requires-Dist: numpy (>=1.17.3)
